instagram_client/__init__.py
instagram_client/instagram.py
instagram_client/api/__init__.py
instagram_client/api/base_api.py
instagram_client/exceptions/__init__.py
instagram_client/exceptions/http_exceptions.py
instagram_client/schemes/__init__.py
instagram_client/schemes/conversation_schemes.py
instagram_client/schemes/user_schemes.py
instagram_client-0.2.4.dist-info/METADATA
instagram_client-0.2.4.dist-info/WHEEL
instagram_client-0.2.4.dist-info/top_level.txt
instagram_client-0.2.4.dist-info/RECORD
