Metadata-Version: 2.4
Name: instagram-client
Version: 0.2.4
Summary: Instagram official api 2.0 client by robosell.uz
Home-page: https://github.com/RoboSell-organization/instagram-client
Author: Abdulvoris
Author-email: erkinovabdulvoris101@gmail.com
Requires-Python: >=3.11
Requires-Dist: requests>=2.0.0
Requires-Dist: python-dateutil>=2.8.0
Requires-Dist: pydantic>=1.9.0
Requires-Dist: typing_extensions>=4.0.0
Dynamic: author
Dynamic: author-email
Dynamic: description
Dynamic: description-content-type
Dynamic: home-page
Dynamic: requires-dist
Dynamic: requires-python
Dynamic: summary
